README.md
setup.py
chachies/__init__.py
chachies/chachies.py
chachies/chachifuncs.py
chachies/descriptors.py
chachies/version.py
chachies.egg-info/PKG-INFO
chachies.egg-info/SOURCES.txt
chachies.egg-info/dependency_links.txt
chachies.egg-info/requires.txt
chachies.egg-info/top_level.txt
chachies/tests/__init__.py
chachies/tests/test_chachifuncs.py
chachies/tests/test_descriptors.py