Metadata-Version: 1.0
Name: chachies
Version: 1.1
Summary: Differential capacity plot visualization and machine learning model for battery chemistry classification
Home-page: https://github.com/tacohen/chachies
Author: The Charged Chinchillas
Author-email: UNKNOWN
License: UNKNOWN
Platform: UNKNOWN
